MANIFEST.in
README.rst
requirements.txt
setup.py
django_tastypie_extendedmodelresource.egg-info/PKG-INFO
django_tastypie_extendedmodelresource.egg-info/SOURCES.txt
django_tastypie_extendedmodelresource.egg-info/dependency_links.txt
django_tastypie_extendedmodelresource.egg-info/not-zip-safe
django_tastypie_extendedmodelresource.egg-info/requires.txt
django_tastypie_extendedmodelresource.egg-info/top_level.txt
extendedmodelresource/__init__.py
extendedmodelresource/extendedmodelresource.py