Metadata-Version: 1.1
Name: django-tastypie-extendedmodelresource
Version: 0.22
Summary: An extension of TastyPie's ModelResource to easily support nested resources, and more.
Home-page: https://github.com/tryolabs/django-tastypie-extendedmodelresource
Author: Alan Descoins, Martín Santos
Author-email: alan@tryolabs.com, santos@tryolabs.com
License: BSD
Keywords: REST RESTful tastypie django resource nested extension
Platform: UNKNOWN
Classifier: Development Status :: 4 - Beta
Classifier: Environment :: Web Environment
Classifier: Framework :: Django
Classifier: Intended Audience :: Developers
Classifier: License :: OSI Approved :: BSD License
Classifier: Operating System :: OS Independent
Classifier: Programming Language :: Python
Classifier: Topic :: Utilities
